{
  "schema_version": "raw-evidence-v2",
  "raw_id": "R-140",
  "title": "NotebookLM升级：AI思考过程更清晰",
  "original_url": "https://x.com/NotebookLM/status/2064084153533165588",
  "canonical_url": "https://x.com/NotebookLM/status/2064084153533165588",
  "source_name": "X：NotebookLM (@NotebookLM)",
  "source_type": "community",
  "source_level": "C",
  "source_level_role": "traceability_only_not_value_score_or_core_gate",
  "evidence_object_type": "community_feedback",
  "evidence_object_usable": false,
  "event_evidence": false,
  "index_only_evidence": false,
  "acquisition_source_level": "M",
  "acquisition_channel": "aihot",
  "research_status": "not_research",
  "search_intent": "",
  "search_path": "",
  "search_path_label": "",
  "author": "",
  "published_at": "2026-06-08T20:36:25.000Z",
  "collected_at": "2026-06-09T02:33:36.699Z",
  "language": "mixed",
  "full_text": "想更详细了解今天的发布吗？以下是新功能和亮点的介绍🧵： 首先：升级版、更周到的聊天体验。 由Gemini 3.5和@Antigravity提供支持，您现在将更清晰地看到AI的思考过程。此外，每个笔记本都有一台安全的云电脑，包含100多种精选软件技能，解锁更深入的研究和更复杂的分析。",
  "clean_text": "想更详细了解今天的发布吗？以下是新功能和亮点的介绍🧵： 首先：升级版、更周到的聊天体验。 由Gemini 3.5和@Antigravity提供支持，您现在将更清晰地看到AI的思考过程。此外，每个笔记本都有一台安全的云电脑，包含100多种精选软件技能，解锁更深入的研究和更复杂的分析。",
  "markdown_snapshot_path": "01-SiteV2/content/01-raw/originals/2026-06-09/r-140-notebooklm升级-ai思考过程更清晰.md",
  "json_snapshot_path": "01-SiteV2/content/01-raw/originals/2026-06-09/r-140-notebooklm升级-ai思考过程更清晰.json",
  "html_snapshot_path": "",
  "screenshot_path": "",
  "fetch_status": "summary-only-low-readable-body",
  "extraction_quality": "failed",
  "extraction_method": "none",
  "readability_score": 0,
  "extractor_diagnostics": {
    "readability_score": 0,
    "text_length": 0,
    "paragraph_count": 0,
    "sentence_count": 0,
    "boilerplate_hits": 0,
    "symbol_ratio": 1,
    "method": "none"
  },
  "has_full_text": false,
  "content_length": 142,
  "fetch_error": "",
  "evidence_completeness": {
    "original_url_status": "present",
    "full_text_status": "missing_or_summary_only",
    "snapshot_status": "present",
    "hash_status": "present",
    "excerpt_status": "present",
    "markdown_snapshot_status": "will_write",
    "json_snapshot_status": "will_write",
    "evidence_hash": "d46ab8b06f9efda2",
    "missing": [
      "missing_full_text"
    ]
  },
  "raw_qc_decision": "allow_with_degradation",
  "raw_qc_downstream_use": "index_watchlist_or_feedback_only",
  "degradation_reasons": [
    "missing_full_text",
    "discovery_or_feedback_source_boundary"
  ],
  "source_volatility": "high",
  "community_name": "X：NotebookLM (@NotebookLM)",
  "capture_scope": "aihot_visible_text",
  "visible_range": "抓取时页面可见正文 / 讨论文本",
  "evidence_level": "discovery_only",
  "discovery_source": "AI HOT",
  "discovery_record": {
    "discovery_title": "NotebookLM升级：AI思考过程更清晰",
    "discovery_summary": "想更详细了解今天的发布吗？以下是新功能和亮点的介绍🧵： 首先：升级版、更周到的聊天体验。 由Gemini 3.5和@Antigravity提供支持，您现在将更清晰地看到AI的思考过程。此外，每个笔记本都有一台安全的云电脑，包含100多种精选软件技能，解锁更深入的研究和更复杂的分析。",
    "source_name": "X：NotebookLM (@NotebookLM)",
    "origin_url": "https://x.com/NotebookLM/status/2064084153533165588",
    "discovered_at": "2026-06-09T02:25:44.680Z",
    "rank_on_page": 129,
    "discovery_status": "discovered"
  },
  "source_role": "discovery_source",
  "origin_fetch_status": "summary_only",
  "paywall_status": "none",
  "block_status": "none",
  "duplicate_status": "unique",
  "url_hash": "7ee1deec96e09c5f",
  "content_hash": "d46ab8b06f9efda2",
  "full_text_hash": "d46ab8b06f9efda2",
  "semantic_hash": "673dc08e13516bf5",
  "duplicate_of": "",
  "first_seen_at": "2026-06-08T20:36:25.000Z",
  "last_seen_at": "2026-06-09T02:33:36.699Z",
  "update_detected": false,
  "key_excerpts": [
    {
      "type": "supporting_context",
      "text": "想更详细了解今天的发布吗？以下是新功能和亮点的介绍🧵： 首先：升级版、更周到的聊天体验。 由Gemini 3.5和@Antigravity提供支持，您现在将更清晰地看到AI的思考过程。此外，每个笔记本都有一台安全的云电脑，包含100多种精选软件技能，解锁更深入的研究和更复杂的分析。",
      "supports": [
        "daily_observation",
        "heatmap"
      ],
      "importance": "high",
      "confidence": "medium"
    },
    {
      "type": "company_action",
      "text": "以下是新功能和亮点的介绍🧵： 首先：升级版、更周到的聊天体验。",
      "supports": [
        "daily_observation",
        "heatmap",
        "change",
        "case",
        "trend"
      ],
      "importance": "high",
      "confidence": "medium"
    },
    {
      "type": "company_action",
      "text": "5和@Antigravity提供支持，您现在将更清晰地看到AI的思考过程。",
      "supports": [
        "daily_observation",
        "heatmap",
        "change",
        "case",
        "trend"
      ],
      "importance": "high",
      "confidence": "medium"
    },
    {
      "type": "supporting_context",
      "text": "此外，每个笔记本都有一台安全的云电脑，包含100多种精选软件技能，解锁更深入的研究和更复杂的分析。",
      "supports": [
        "daily_observation",
        "heatmap"
      ],
      "importance": "high",
      "confidence": "medium"
    }
  ],
  "business_elements": {
    "companies": [
      "X",
      "NotebookLM (@NotebookLM)"
    ],
    "products": [
      "Gemini"
    ],
    "people": [],
    "industries": [],
    "roles": [],
    "workflows": [
      "权限 / 安全治理"
    ],
    "business_actions": [
      "发布 / 推出"
    ],
    "affected_departments": [
      "IT / 安全"
    ],
    "numbers": [
      "3.5",
      "100"
    ],
    "quotes": []
  },
  "evidence_seed": {
    "company_actions": [
      "以下是新功能和亮点的介绍🧵： 首先：升级版、更周到的聊天体验。",
      "5和@Antigravity提供支持，您现在将更清晰地看到AI的思考过程。"
    ],
    "case_details": [],
    "workflow_changes": [],
    "before_after_clues": [
      "可能涉及 权限 / 安全治理 的前后变化，需要二搜补足变化前流程。"
    ],
    "affected_roles": [],
    "risks_or_constraints": [
      "想更详细了解今天的发布吗？以下是新功能和亮点的介绍🧵： 首先：升级版、更周到的聊天体验。 由Gemini 3.5和@Antigravity提供支持，您现在将更清晰地看到AI的思考过程。此外，每个笔记本都有一台安全的云电脑，包含100多种精选软件技能，解锁更深入的研究和更复杂的分析。",
      "此外，每个笔记本都有一台安全的云电脑，包含100多种精选软件技能，解锁更深入的研究和更复杂的分析。"
    ]
  },
  "guanlan_scores": {
    "importance_type": "important_product_or_service",
    "importance_score": 4,
    "importance_reason": "new product or service; rubric=4 concrete important change",
    "supporting_signals": [
      "commercial_or_risk_context"
    ],
    "novelty": 3,
    "evidence_strength": 2,
    "case_richness": 3,
    "trend_relevance": 4,
    "guanlan_relevance": 5,
    "emerging_signal_score": 3
  },
  "usable_for": {
    "viewpoint": false,
    "case": false,
    "change": false,
    "trend": false,
    "daily_observation": false,
    "heatmap": false,
    "briefing": false,
    "emerging_pool": false,
    "user_feedback_pool": false,
    "watchlist": false
  },
  "pool_routes": [
    "discard"
  ],
  "change_action_detected": true,
  "evidence_eligibility": "blocked",
  "evidence_block_reason": "not_event_case_or_trend_evidence",
  "missing_information": [
    "证据对象不可用：疑似索引页、目录页、薄文本或非可用证据对象",
    "没有具体客户或真实企业案例",
    "没有可用全文快照"
  ],
  "raw_status": "ignored",
  "copyright_note": "local research archive only",
  "markdown_snapshot": "# NotebookLM升级：AI思考过程更清晰\n\n- raw_id: R-140\n- original_url: https://x.com/NotebookLM/status/2064084153533165588\n- source_name: X：NotebookLM (@NotebookLM)\n- collected_at: 2026-06-09T02:33:36.699Z\n\n## clean_text\n\n想更详细了解今天的发布吗？以下是新功能和亮点的介绍🧵： 首先：升级版、更周到的聊天体验。 由Gemini 3.5和@Antigravity提供支持，您现在将更清晰地看到AI的思考过程。此外，每个笔记本都有一台安全的云电脑，包含100多种精选软件技能，解锁更深入的研究和更复杂的分析。\n\n## full_text\n\n想更详细了解今天的发布吗？以下是新功能和亮点的介绍🧵： 首先：升级版、更周到的聊天体验。 由Gemini 3.5和@Antigravity提供支持，您现在将更清晰地看到AI的思考过程。此外，每个笔记本都有一台安全的云电脑，包含100多种精选软件技能，解锁更深入的研究和更复杂的分析。\n\n## extraction_diagnostics\n\n- extraction_method: none\n- readability_score: 0\n- fetch_status: summary-only-low-readable-body\n- extraction_quality: failed\n\n## key_excerpts\n\n1. [supporting_context / daily_observation, heatmap / high] 想更详细了解今天的发布吗？以下是新功能和亮点的介绍🧵： 首先：升级版、更周到的聊天体验。 由Gemini 3.5和@Antigravity提供支持，您现在将更清晰地看到AI的思考过程。此外，每个笔记本都有一台安全的云电脑，包含100多种精选软件技能，解锁更深入的研究和更复杂的分析。\n2. [company_action / daily_observation, heatmap, change, case, trend / high] 以下是新功能和亮点的介绍🧵： 首先：升级版、更周到的聊天体验。\n3. [company_action / daily_observation, heatmap, change, case, trend / high] 5和@Antigravity提供支持，您现在将更清晰地看到AI的思考过程。\n4. [supporting_context / daily_observation, heatmap / high] 此外，每个笔记本都有一台安全的云电脑，包含100多种精选软件技能，解锁更深入的研究和更复杂的分析。\n"
}
