{
  "schema_version": "raw-evidence-v2",
  "raw_id": "R-049",
  "title": "PaddleOCR 3.5：使用Transformers后端运行OCR和文档解析任务",
  "original_url": "https://huggingface.co/blog/PaddlePaddle/paddleocr-transformers",
  "canonical_url": "https://huggingface.co/blog/PaddlePaddle/paddleocr-transformers",
  "source_name": "Hugging Face：Blog（RSS）",
  "source_type": "official",
  "source_level": "S",
  "acquisition_source_level": "M",
  "acquisition_channel": "aihot",
  "research_status": "not_research",
  "search_intent": "",
  "search_path": "",
  "search_path_label": "",
  "author": "",
  "published_at": "2026-05-18T15:12:46.000Z",
  "collected_at": "2026-05-19T05:27:30.048Z",
  "language": "mixed",
  "full_text": "PaddleOCR 发布 3.5 版本，正式将 Transformers 确立为运行 PP-OCRv5 及 PaddleOCR-VL 1.5 模型的可选推理后端之一。此次更新引入了更灵活的 `engine` 与 `engine_config` 参数，允许开发者自主选择后端并配置数据类型、设备等选项。其核心价值在于，显著降低了将文档处理能力集成至以 Transformers 为中心的主流开发栈（如 RAG、智能体、文档AI）的门槛，使开发者能更便捷地利用现有生态，减少集成阻力，从而专注于下游应用构建。",
  "clean_text": "PaddleOCR 发布 3.5 版本，正式将 Transformers 确立为运行 PP-OCRv5 及 PaddleOCR-VL 1.5 模型的可选推理后端之一。此次更新引入了更灵活的 `engine` 与 `engine_config` 参数，允许开发者自主选择后端并配置数据类型、设备等选项。其核心价值在于，显著降低了将文档处理能力集成至以 Transformers 为中心的主流开发栈（如 RAG、智能体、文档AI）的门槛，使开发者能更便捷地利用现有生态，减少集成阻力，从而专注于下游应用构建。",
  "markdown_snapshot_path": "01-SiteV2/content/01-raw/originals/2026-05-19/r-049-paddleocr-3-5-使用transformers后端运行ocr和文档解析任务.md",
  "json_snapshot_path": "01-SiteV2/content/01-raw/originals/2026-05-19/r-049-paddleocr-3-5-使用transformers后端运行ocr和文档解析任务.json",
  "html_snapshot_path": "",
  "screenshot_path": "",
  "fetch_status": "fetch-failed-fallback-visible-text",
  "extraction_quality": "failed",
  "has_full_text": false,
  "content_length": 252,
  "fetch_error": "fetch failed (code=ECONNRESET errno=-4077 syscall=read)",
  "source_volatility": "medium",
  "community_name": "",
  "capture_scope": "aihot_visible_text",
  "visible_range": "仅保留采集通道当时可见文本，未抓到原页面正文",
  "evidence_level": "discovery_only",
  "discovery_source": "AI HOT",
  "discovery_record": {
    "discovery_title": "PaddleOCR 3.5：使用Transformers后端运行OCR和文档解析任务",
    "discovery_summary": "PaddleOCR 发布 3.5 版本，正式将 Transformers 确立为运行 PP-OCRv5 及 PaddleOCR-VL 1.5 模型的可选推理后端之一。此次更新引入了更灵活的 `engine` 与 `engine_config` 参数，允许开发者自主选择后端并配置数据类型、设备等选项。其核心价值在于，显著降低了将文档处理能力集成至以 Transformers 为中心的主流开发栈（如 RAG、智能体、文档AI）的门槛，使开发者能更便捷地利用现有生态，减少集成阻力，从而专注于下游应用构建。",
    "source_name": "Hugging Face：Blog（RSS）",
    "origin_url": "https://huggingface.co/blog/PaddlePaddle/paddleocr-transformers",
    "discovered_at": "2026-05-19T05:22:41.582Z",
    "rank_on_page": 93,
    "discovery_status": "discovered"
  },
  "source_role": "discovery_source",
  "origin_fetch_status": "failed",
  "paywall_status": "none",
  "block_status": "none",
  "duplicate_status": "unique",
  "url_hash": "0e90042cc61fe001",
  "content_hash": "b652defaff75488e",
  "full_text_hash": "b652defaff75488e",
  "semantic_hash": "ef0c3dd038cf5a08",
  "duplicate_of": "",
  "first_seen_at": "2026-05-18T15:12:46.000Z",
  "last_seen_at": "2026-05-19T05:27:30.048Z",
  "update_detected": false,
  "key_excerpts": [
    {
      "type": "product_update",
      "text": "PaddleOCR 发布 3.5 版本，正式将 Transformers 确立为运行 PP-OCRv5 及 PaddleOCR-VL 1.5 模型的可选推理后端之一。此次更新引入了更灵活的 `engine` 与 `engine_config` 参数，允许开发者自主选择后端并配置数据类型、设备等选项。其核心价值在于，显著降低了将文档处理能力集成至以 Transformers 为中心的主流开发栈（如 RAG、智能体、文档AI）的门槛，使开发者能更便捷地利用现有生态，减少集成阻力，从而专注于下游应用构建。",
      "supports": [
        "daily_observation",
        "heatmap",
        "change"
      ],
      "importance": "high",
      "confidence": "medium"
    },
    {
      "type": "company_action",
      "text": "5 版本，正式将 Transformers 确立为运行 PP-OCRv5 及 PaddleOCR-VL 1.",
      "supports": [
        "daily_observation",
        "heatmap",
        "change",
        "case",
        "trend"
      ],
      "importance": "high",
      "confidence": "medium"
    },
    {
      "type": "product_update",
      "text": "此次更新引入了更灵活的 `engine` 与 `engine_config` 参数，允许开发者自主选择后端并配置数据类型、设备等选项。",
      "supports": [
        "daily_observation",
        "heatmap",
        "change"
      ],
      "importance": "high",
      "confidence": "medium"
    },
    {
      "type": "product_update",
      "text": "其核心价值在于，显著降低了将文档处理能力集成至以 Transformers 为中心的主流开发栈（如 RAG、智能体、文档AI）的门槛，使开发者能更便捷地利用现有生态，减少集成阻力，从而专注于下游应用构建。",
      "supports": [
        "daily_observation",
        "heatmap",
        "change"
      ],
      "importance": "high",
      "confidence": "medium"
    }
  ],
  "business_elements": {
    "companies": [
      "Hugging Face",
      "Blog（RSS）"
    ],
    "products": [],
    "people": [],
    "industries": [
      "开发者工具"
    ],
    "roles": [
      "开发者 / 工程团队"
    ],
    "workflows": [
      "部署 / 集成交付"
    ],
    "business_actions": [
      "发布 / 推出"
    ],
    "affected_departments": [],
    "numbers": [
      "3.5",
      "5",
      "1.5"
    ],
    "quotes": []
  },
  "evidence_seed": {
    "company_actions": [
      "PaddleOCR 发布 3.5 版本，正式将 Transformers 确立为运行 PP-OCRv5 及 PaddleOCR-VL 1.5 模型的可选推理后端之一。此次更新引入了更灵活的 `engine` 与 `engine_config` 参数，允许开发者自主选择后端并配置数据类型、设备等选项。其核心价值在于，显著降低了将文档处理能力集成至以 Transformers 为中心的主流开发栈（如 RAG、智能体、文档AI）的门槛，使开发者能更便捷地利用现有生态，减少集成阻力，从而专注于下游应用构建。",
      "5 版本，正式将 Transformers 确立为运行 PP-OCRv5 及 PaddleOCR-VL 1.",
      "此次更新引入了更灵活的 `engine` 与 `engine_config` 参数，允许开发者自主选择后端并配置数据类型、设备等选项。"
    ],
    "case_details": [],
    "workflow_changes": [],
    "before_after_clues": [
      "可能涉及 部署 / 集成交付 的前后变化，需要二搜补足变化前流程。"
    ],
    "affected_roles": [
      "开发者 / 工程团队"
    ],
    "risks_or_constraints": []
  },
  "guanlan_scores": {
    "commercial_value": 5,
    "novelty": 3,
    "evidence_strength": 2,
    "case_richness": 3,
    "trend_relevance": 4,
    "guanlan_relevance": 5,
    "emerging_signal_score": 2
  },
  "usable_for": {
    "viewpoint": false,
    "case": false,
    "change": false,
    "trend": false,
    "daily_observation": false,
    "heatmap": true,
    "briefing": false,
    "emerging_pool": false,
    "user_feedback_pool": false,
    "watchlist": true
  },
  "pool_routes": [
    "watchlist"
  ],
  "missing_information": [
    "没有具体客户或真实企业案例",
    "没有可用全文快照"
  ],
  "raw_status": "ignored",
  "copyright_note": "local research archive only",
  "markdown_snapshot": "# PaddleOCR 3.5：使用Transformers后端运行OCR和文档解析任务\n\n- raw_id: R-049\n- original_url: https://huggingface.co/blog/PaddlePaddle/paddleocr-transformers\n- source_name: Hugging Face：Blog（RSS）\n- collected_at: 2026-05-19T05:27:30.048Z\n\n## clean_text\n\nPaddleOCR 发布 3.5 版本，正式将 Transformers 确立为运行 PP-OCRv5 及 PaddleOCR-VL 1.5 模型的可选推理后端之一。此次更新引入了更灵活的 `engine` 与 `engine_config` 参数，允许开发者自主选择后端并配置数据类型、设备等选项。其核心价值在于，显著降低了将文档处理能力集成至以 Transformers 为中心的主流开发栈（如 RAG、智能体、文档AI）的门槛，使开发者能更便捷地利用现有生态，减少集成阻力，从而专注于下游应用构建。\n\n## full_text\n\nPaddleOCR 发布 3.5 版本，正式将 Transformers 确立为运行 PP-OCRv5 及 PaddleOCR-VL 1.5 模型的可选推理后端之一。此次更新引入了更灵活的 `engine` 与 `engine_config` 参数，允许开发者自主选择后端并配置数据类型、设备等选项。其核心价值在于，显著降低了将文档处理能力集成至以 Transformers 为中心的主流开发栈（如 RAG、智能体、文档AI）的门槛，使开发者能更便捷地利用现有生态，减少集成阻力，从而专注于下游应用构建。\n\n## key_excerpts\n\n1. [product_update / daily_observation, heatmap, change / high] PaddleOCR 发布 3.5 版本，正式将 Transformers 确立为运行 PP-OCRv5 及 PaddleOCR-VL 1.5 模型的可选推理后端之一。此次更新引入了更灵活的 `engine` 与 `engine_config` 参数，允许开发者自主选择后端并配置数据类型、设备等选项。其核心价值在于，显著降低了将文档处理能力集成至以 Transformers 为中心的主流开发栈（如 RAG、智能体、文档AI）的门槛，使开发者能更便捷地利用现有生态，减少集成阻力，从而专注于下游应用构建。\n2. [company_action / daily_observation, heatmap, change, case, trend / high] 5 版本，正式将 Transformers 确立为运行 PP-OCRv5 及 PaddleOCR-VL 1.\n3. [product_update / daily_observation, heatmap, change / high] 此次更新引入了更灵活的 `engine` 与 `engine_config` 参数，允许开发者自主选择后端并配置数据类型、设备等选项。\n4. [product_update / daily_observation, heatmap, change / high] 其核心价值在于，显著降低了将文档处理能力集成至以 Transformers 为中心的主流开发栈（如 RAG、智能体、文档AI）的门槛，使开发者能更便捷地利用现有生态，减少集成阻力，从而专注于下游应用构建。\n"
}
