{
  "schema_version": "raw-evidence-v2",
  "raw_id": "R-013",
  "title": "First Concepts raises $1M to develop AI-native OS for creative work - Tech.eu",
  "original_url": "https://tech.eu/2026/03/17/first-concepts-raises-1m-to-develop-ai-native-os-for-creative-work/",
  "canonical_url": "https://tech.eu/2026/03/17/first-concepts-raises-1m-to-develop-ai-native-os-for-creative-work",
  "source_name": "keyword search / Anysearch",
  "source_type": "web",
  "source_level": "B",
  "source_level_role": "traceability_only_not_value_score_or_core_gate",
  "evidence_object_type": "case_or_customer",
  "evidence_object_usable": true,
  "event_evidence": true,
  "index_only_evidence": false,
  "acquisition_source_level": "M",
  "acquisition_channel": "keyword-search",
  "research_status": "not_research",
  "search_intent": "find_startups",
  "search_path": "capital_startup",
  "search_path_label": "资本与创业公司路径",
  "author": "",
  "published_at": "",
  "collected_at": "2026-06-02T03:48:56.930Z",
  "language": "mixed",
  "full_text": "Software development\nFirst Concepts raises $1M to develop AI-native OS for creative work\nFirst Concepts builds AI software that helps creative teams develop ideas and manage context across creative workflows.\nTamara Djurickovic\n17 March 2026\nShare\nFacebook\nTwitter\nLinkedin\nShare\nSend email\nCopy link\nLondon-based\nstartup First Concepts , an AI-powered workspace for early-stage creative work,\nhas raised $1 million in pre-seed funding less than nine months after its\nfounding. The round was led by Arāya Ventures alongside Antler . Additional\nparticipants included industry leaders such as Jez Jowett (former Managing\nPartner at Havas), Nathan McDonald (founder of We Are Social), Sean Williams and\nSam Winward (partners at UNKNOWN), and Hugo Rodger Brown (founder of YunoJuno).\nCreative\nagencies often work on multiple pitches each month, investing significant time\nand resources in the process. However, much of this time is spent rebuilding\ncontext across fragmented tools and systems.\nFirst\nConcepts aims to address this challenge by introducing an AI layer that sits\nabove existing tools and coordinates leading AI models through a shared context\nand “taste” framework. This approach helps creative teams maintain consistency\nin ideas, brand identity, and decision-making throughout the pitching process.\nFounded\nby Conor Hoey , Polina Sali , and Marin Godechot , who bring experience in design,\nAI, and product development, First Concepts has developed a system that brings\ncontext and creative judgment to the development of pitches.\nThe\nproduct is built around three core components: a Creative DNA engine that\nlearns individual and brand preferences, a unified interface that treats\ncontext as the central source of information, and a tool-agnostic\ninfrastructure that connects creative tools while maintaining coherence across\noutputs.\nExplaining\nthe company’s vision, Conor Hoey, co-founder and CEO of First Concepts, said:\nFirst\nConcepts has a simple mission to transform creative context from something\nfragile and ephemeral into a structured, compounding asset. We are building an\noperating system that understands the value of creative thinking and taste.\nThis will transform creative workflows for teams around the world.\nThe new\nfunding will be used to further develop the company’s AI-native workspace for\ncreative work.\nArtificial Intelligence\nFirst Concepts\nWrite Comment\nFirst Concepts raises $1M to develop AI-native OS for creative work\nComments\nWould you like to write the first comment?\nLogin to post comments\nFollow the developments in the technology world. What would you like us to deliver to you?",
  "clean_text": "Software development\nFirst Concepts raises $1M to develop AI-native OS for creative work\nFirst Concepts builds AI software that helps creative teams develop ideas and manage context across creative workflows.\nTamara Djurickovic\n17 March 2026\nShare\nFacebook\nTwitter\nLinkedin\nShare\nSend email\nCopy link\nLondon-based\nstartup First Concepts , an AI-powered workspace for early-stage creative work,\nhas raised $1 million in pre-seed funding less than nine months after its\nfounding. The round was led by Arāya Ventures alongside Antler . Additional\nparticipants included industry leaders such as Jez Jowett (former Managing\nPartner at Havas), Nathan McDonald (founder of We Are Social), Sean Williams and\nSam Winward (partners at UNKNOWN), and Hugo Rodger Brown (founder of YunoJuno).\nCreative\nagencies often work on multiple pitches each month, investing significant time\nand resources in the process. However, much of this time is spent rebuilding\ncontext across fragmented tools and systems.\nFirst\nConcepts aims to address this challenge by introducing an AI layer that sits\nabove existing tools and coordinates leading AI models through a shared context\nand “taste” framework. This approach helps creative teams maintain consistency\nin ideas, brand identity, and decision-making throughout the pitching process.\nFounded\nby Conor Hoey , Polina Sali , and Marin Godechot , who bring experience in design,\nAI, and product development, First Concepts has developed a system that brings\ncontext and creative judgment to the development of pitches.\nThe\nproduct is built around three core components: a Creative DNA engine that\nlearns individual and brand preferences, a unified interface that treats\ncontext as the central source of information, and a tool-agnostic\ninfrastructure that connects creative tools while maintaining coherence across\noutputs.\nExplaining\nthe company’s vision, Conor Hoey, co-founder and CEO of First Concepts, said:\nFirst\nConcepts has a simple mission to transform creative context from something\nfragile and ephemeral into a structured, compounding asset. We are building an\noperating system that understands the value of creative thinking and taste.\nThis will transform creative workflows for teams around the world.\nThe new\nfunding will be used to further develop the company’s AI-native workspace for\ncreative work.\nArtificial Intelligence\nFirst Concepts\nWrite Comment\nFirst Concepts raises $1M to develop AI-native OS for creative work\nComments\nWould you like to write the first comment?\nLogin to post comments\nFollow the developments in the technology world. What would you like us to deliver to you?",
  "markdown_snapshot_path": "01-SiteV2/content/01-raw/originals/2026-06-02/r-013-first-concepts-raises-1m-to-develop-ai-native-os-for-creative-work-tec.md",
  "json_snapshot_path": "01-SiteV2/content/01-raw/originals/2026-06-02/r-013-first-concepts-raises-1m-to-develop-ai-native-os-for-creative-work-tec.json",
  "html_snapshot_path": "",
  "screenshot_path": "",
  "fetch_status": "fetched-readable-text-article",
  "extraction_quality": "high",
  "extraction_method": "article",
  "readability_score": 81,
  "extractor_diagnostics": {
    "readability_score": 81,
    "text_length": 2626,
    "paragraph_count": 34,
    "sentence_count": 17,
    "boilerplate_hits": 0,
    "symbol_ratio": 0,
    "method": "article"
  },
  "has_full_text": true,
  "content_length": 2626,
  "fetch_error": "",
  "evidence_completeness": {
    "original_url_status": "present",
    "full_text_status": "present",
    "snapshot_status": "present",
    "hash_status": "present",
    "excerpt_status": "present",
    "markdown_snapshot_status": "will_write",
    "json_snapshot_status": "will_write",
    "evidence_hash": "290464341ec7404f",
    "missing": []
  },
  "raw_qc_decision": "allow",
  "raw_qc_downstream_use": "eligible_after_qc",
  "degradation_reasons": [],
  "source_volatility": "low",
  "community_name": "",
  "capture_scope": "article_text",
  "visible_range": "抓取时页面可见正文 / 讨论文本",
  "evidence_level": "core_evidence_candidate",
  "discovery_source": "",
  "discovery_record": null,
  "source_role": "resolved_original_source",
  "origin_fetch_status": "",
  "paywall_status": "none",
  "block_status": "none",
  "duplicate_status": "unique",
  "url_hash": "c9fe047797d5a191",
  "content_hash": "290464341ec7404f",
  "full_text_hash": "290464341ec7404f",
  "semantic_hash": "9cf5135769615682",
  "duplicate_of": "",
  "first_seen_at": "2026-06-02T03:48:56.930Z",
  "last_seen_at": "2026-06-02T03:48:56.930Z",
  "update_detected": false,
  "key_excerpts": [
    {
      "type": "funding",
      "text": "First Concepts raises $1M to develop AI-native OS for creative work London-based startup First Concepts, an AI-powered workspace for early-stage creative work, has raised $1 million in pre-seed funding less than nine months after its founding. The round was led by Arāya Ventures alongside Antler. Additional participants included industry leaders such as Jez Jowett (former Managing Partner at Havas), Nathan McDonald (founder of We Are Social), Sean Williams and Sam Winward (partners at UNKNOWN), and Hugo Rodger Brow",
      "supports": [
        "daily_observation",
        "heatmap",
        "trend"
      ],
      "importance": "high",
      "confidence": "high"
    },
    {
      "type": "funding",
      "text": "Software development First Concepts raises $1M to develop AI-native OS for creative work First Concepts builds AI software that helps creative teams develop ideas and manage context across creative workflows.",
      "supports": [
        "daily_observation",
        "heatmap",
        "trend"
      ],
      "importance": "high",
      "confidence": "high"
    },
    {
      "type": "funding",
      "text": "Tamara Djurickovic 17 March 2026 Share Facebook Twitter Linkedin Share Send email Copy link London-based startup First Concepts , an AI-powered workspace for early-stage creative work, has raised $1 million in pre-seed funding less than nine months after its founding.",
      "supports": [
        "daily_observation",
        "heatmap",
        "trend"
      ],
      "importance": "high",
      "confidence": "high"
    },
    {
      "type": "company_action",
      "text": "The round was led by Arāya Ventures alongside Antler .",
      "supports": [
        "daily_observation",
        "heatmap",
        "change",
        "case",
        "trend"
      ],
      "importance": "high",
      "confidence": "high"
    },
    {
      "type": "company_action",
      "text": "Additional participants included industry leaders such as Jez Jowett (former Managing Partner at Havas), Nathan McDonald (founder of We Are Social), Sean Williams and Sam Winward (partners at UNKNOWN), and Hugo Rodger Brown (founder of YunoJuno).",
      "supports": [
        "daily_observation",
        "heatmap",
        "change",
        "case",
        "trend"
      ],
      "importance": "high",
      "confidence": "high"
    },
    {
      "type": "workflow_change",
      "text": "Creative agencies often work on multiple pitches each month, investing significant time and resources in the process.",
      "supports": [
        "daily_observation",
        "heatmap",
        "change",
        "case",
        "trend"
      ],
      "importance": "high",
      "confidence": "high"
    }
  ],
  "business_elements": {
    "companies": [
      "keyword search",
      "Anysearch"
    ],
    "products": [],
    "people": [],
    "industries": [],
    "roles": [],
    "workflows": [],
    "business_actions": [
      "合作 / 联盟",
      "融资 / 投资"
    ],
    "affected_departments": [
      "IT / 安全"
    ],
    "numbers": [
      "$1M",
      "$1 million",
      "77.667",
      "17 M",
      "2026"
    ],
    "quotes": []
  },
  "evidence_seed": {
    "company_actions": [
      "First Concepts raises $1M to develop AI-native OS for creative work London-based startup First Concepts, an AI-powered workspace for early-stage creative work, has raised $1 million in pre-seed funding less than nine months after its founding. The round was led by Arāya Ventures alongside Antler. Additional participants included industry leaders such as Jez Jowett (former Managing Partner at Havas), Nathan McDonald (founder of We Are Social), Sean Williams and Sam Winward (partners at UNKNOWN), and Hugo Rodger Brow",
      "Software development First Concepts raises $1M to develop AI-native OS for creative work First Concepts builds AI software that helps creative teams develop ideas and manage context across creative workflows.",
      "Tamara Djurickovic 17 March 2026 Share Facebook Twitter Linkedin Share Send email Copy link London-based startup First Concepts , an AI-powered workspace for early-stage creative work, has raised $1 million in pre-seed funding less than nine months after its founding."
    ],
    "case_details": [],
    "workflow_changes": [
      "Creative agencies often work on multiple pitches each month, investing significant time and resources in the process."
    ],
    "before_after_clues": [],
    "affected_roles": [],
    "risks_or_constraints": []
  },
  "guanlan_scores": {
    "importance_type": "important_funding",
    "importance_score": 5,
    "importance_reason": "funding or investment event; rubric=5 major/platform/industry-shaping",
    "supporting_signals": [
      "adoption_context"
    ],
    "novelty": 3,
    "evidence_strength": 4,
    "case_richness": 3,
    "trend_relevance": 4,
    "guanlan_relevance": 5,
    "emerging_signal_score": 5
  },
  "usable_for": {
    "viewpoint": false,
    "case": true,
    "change": true,
    "trend": true,
    "daily_observation": true,
    "heatmap": true,
    "briefing": true,
    "emerging_pool": true,
    "user_feedback_pool": false,
    "watchlist": true
  },
  "pool_routes": [
    "core_pool",
    "emerging_pool"
  ],
  "change_action_detected": true,
  "evidence_eligibility": "eligible",
  "evidence_block_reason": "",
  "missing_information": [
    "没有具体客户或真实企业案例",
    "没有变化前后流程线索"
  ],
  "raw_status": "pooled",
  "copyright_note": "local research archive only",
  "markdown_snapshot": "# First Concepts raises $1M to develop AI-native OS for creative work - Tech.eu\n\n- raw_id: R-013\n- original_url: https://tech.eu/2026/03/17/first-concepts-raises-1m-to-develop-ai-native-os-for-creative-work/\n- source_name: keyword search / Anysearch\n- collected_at: 2026-06-02T03:48:56.930Z\n\n## clean_text\n\nSoftware development\nFirst Concepts raises $1M to develop AI-native OS for creative work\nFirst Concepts builds AI software that helps creative teams develop ideas and manage context across creative workflows.\nTamara Djurickovic\n17 March 2026\nShare\nFacebook\nTwitter\nLinkedin\nShare\nSend email\nCopy link\nLondon-based\nstartup First Concepts , an AI-powered workspace for early-stage creative work,\nhas raised $1 million in pre-seed funding less than nine months after its\nfounding. The round was led by Arāya Ventures alongside Antler . Additional\nparticipants included industry leaders such as Jez Jowett (former Managing\nPartner at Havas), Nathan McDonald (founder of We Are Social), Sean Williams and\nSam Winward (partners at UNKNOWN), and Hugo Rodger Brown (founder of YunoJuno).\nCreative\nagencies often work on multiple pitches each month, investing significant time\nand resources in the process. However, much of this time is spent rebuilding\ncontext across fragmented tools and systems.\nFirst\nConcepts aims to address this challenge by introducing an AI layer that sits\nabove existing tools and coordinates leading AI models through a shared context\nand “taste” framework. This approach helps creative teams maintain consistency\nin ideas, brand identity, and decision-making throughout the pitching process.\nFounded\nby Conor Hoey , Polina Sali , and Marin Godechot , who bring experience in design,\nAI, and product development, First Concepts has developed a system that brings\ncontext and creative judgment to the development of pitches.\nThe\nproduct is built around three core components: a Creative DNA engine that\nlearns individual and brand preferences, a unified interface that treats\ncontext as the central source of information, and a tool-agnostic\ninfrastructure that connects creative tools while maintaining coherence across\noutputs.\nExplaining\nthe company’s vision, Conor Hoey, co-founder and CEO of First Concepts, said:\nFirst\nConcepts has a simple mission to transform creative context from something\nfragile and ephemeral into a structured, compounding asset. We are building an\noperating system that understands the value of creative thinking and taste.\nThis will transform creative workflows for teams around the world.\nThe new\nfunding will be used to further develop the company’s AI-native workspace for\ncreative work.\nArtificial Intelligence\nFirst Concepts\nWrite Comment\nFirst Concepts raises $1M to develop AI-native OS for creative work\nComments\nWould you like to write the first comment?\nLogin to post comments\nFollow the developments in the technology world. What would you like us to deliver to you?\n\n## full_text\n\nSoftware development\nFirst Concepts raises $1M to develop AI-native OS for creative work\nFirst Concepts builds AI software that helps creative teams develop ideas and manage context across creative workflows.\nTamara Djurickovic\n17 March 2026\nShare\nFacebook\nTwitter\nLinkedin\nShare\nSend email\nCopy link\nLondon-based\nstartup First Concepts , an AI-powered workspace for early-stage creative work,\nhas raised $1 million in pre-seed funding less than nine months after its\nfounding. The round was led by Arāya Ventures alongside Antler . Additional\nparticipants included industry leaders such as Jez Jowett (former Managing\nPartner at Havas), Nathan McDonald (founder of We Are Social), Sean Williams and\nSam Winward (partners at UNKNOWN), and Hugo Rodger Brown (founder of YunoJuno).\nCreative\nagencies often work on multiple pitches each month, investing significant time\nand resources in the process. However, much of this time is spent rebuilding\ncontext across fragmented tools and systems.\nFirst\nConcepts aims to address this challenge by introducing an AI layer that sits\nabove existing tools and coordinates leading AI models through a shared context\nand “taste” framework. This approach helps creative teams maintain consistency\nin ideas, brand identity, and decision-making throughout the pitching process.\nFounded\nby Conor Hoey , Polina Sali , and Marin Godechot , who bring experience in design,\nAI, and product development, First Concepts has developed a system that brings\ncontext and creative judgment to the development of pitches.\nThe\nproduct is built around three core components: a Creative DNA engine that\nlearns individual and brand preferences, a unified interface that treats\ncontext as the central source of information, and a tool-agnostic\ninfrastructure that connects creative tools while maintaining coherence across\noutputs.\nExplaining\nthe company’s vision, Conor Hoey, co-founder and CEO of First Concepts, said:\nFirst\nConcepts has a simple mission to transform creative context from something\nfragile and ephemeral into a structured, compounding asset. We are building an\noperating system that understands the value of creative thinking and taste.\nThis will transform creative workflows for teams around the world.\nThe new\nfunding will be used to further develop the company’s AI-native workspace for\ncreative work.\nArtificial Intelligence\nFirst Concepts\nWrite Comment\nFirst Concepts raises $1M to develop AI-native OS for creative work\nComments\nWould you like to write the first comment?\nLogin to post comments\nFollow the developments in the technology world. What would you like us to deliver to you?\n\n## extraction_diagnostics\n\n- extraction_method: article\n- readability_score: 81\n- fetch_status: fetched-readable-text-article\n- extraction_quality: high\n\n## key_excerpts\n\n1. [funding / daily_observation, heatmap, trend / high] First Concepts raises $1M to develop AI-native OS for creative work London-based startup First Concepts, an AI-powered workspace for early-stage creative work, has raised $1 million in pre-seed funding less than nine months after its founding. The round was led by Arāya Ventures alongside Antler. Additional participants included industry leaders such as Jez Jowett (former Managing Partner at Havas), Nathan McDonald (founder of We Are Social), Sean Williams and Sam Winward (partners at UNKNOWN), and Hugo Rodger Brow\n2. [funding / daily_observation, heatmap, trend / high] Software development First Concepts raises $1M to develop AI-native OS for creative work First Concepts builds AI software that helps creative teams develop ideas and manage context across creative workflows.\n3. [funding / daily_observation, heatmap, trend / high] Tamara Djurickovic 17 March 2026 Share Facebook Twitter Linkedin Share Send email Copy link London-based startup First Concepts , an AI-powered workspace for early-stage creative work, has raised $1 million in pre-seed funding less than nine months after its founding.\n4. [company_action / daily_observation, heatmap, change, case, trend / high] The round was led by Arāya Ventures alongside Antler .\n5. [company_action / daily_observation, heatmap, change, case, trend / high] Additional participants included industry leaders such as Jez Jowett (former Managing Partner at Havas), Nathan McDonald (founder of We Are Social), Sean Williams and Sam Winward (partners at UNKNOWN), and Hugo Rodger Brown (founder of YunoJuno).\n6. [workflow_change / daily_observation, heatmap, change, case, trend / high] Creative agencies often work on multiple pitches each month, investing significant time and resources in the process.\n"
}
