{
  "schema_version": "raw-evidence-v2",
  "raw_id": "R-087",
  "title": "Vertical AI SaaS: What Founders Need to Know in 2026 | L40°",
  "original_url": "https://www.l40.com/insights/vertical-ai-saas",
  "canonical_url": "https://l40.com/insights/vertical-ai-saas",
  "source_name": "keyword search / Tavily",
  "source_type": "web",
  "source_level": "B",
  "source_level_role": "traceability_only_not_value_score_or_core_gate",
  "evidence_object_type": "case_or_customer",
  "evidence_object_usable": true,
  "event_evidence": true,
  "index_only_evidence": false,
  "acquisition_source_level": "M",
  "acquisition_channel": "keyword-search",
  "research_status": "not_research",
  "search_intent": "find_customer_case",
  "search_path": "industry_landing",
  "search_path_label": "行业落地路径",
  "enterprise_ai_transformation_lens": false,
  "enterprise_ai_transformation_stage": "",
  "enterprise_ai_transformation_reason": "",
  "author": "",
  "published_at": "",
  "collected_at": "2026-06-25T03:26:00.697Z",
  "language": "mixed",
  "full_text": "Transactions INSIGHTS\nABOUT US\nContact Us\nRelated Insights\nNews & Trends\n6/17/2026\nTop SaaS News: August 2025 Recap for Founders\nTop SaaS Industry News: August 2025 Recap for Founders\nAugust 2025 SaaS news: PE bets on platforms, Figma & Circle IPOs reset valuations, and what it means for founders planning their next move.\nNews & Trends\n6/17/2026\nAI Due Diligence: Revolutionizing Deal Assessments\nDiscover how AI due diligence is transforming M&A transactions, enhancing efficiency and accuracy. Read on to understand its impact on the future of deals.\nNews & Trends\n6/17/2026\nWhat to know about AI rollups\nAI Rollups in 2026: What Founders Need to Know\nLearn what AI Rollups are, what buyers want, and what SaaS founders need to know about these type of deals.\nWhere You Can\nFind Us\nWith offices in Miami, Lisbon and Madrid, L40° bridges global markets to deliver impactful results. Our expertise and international reach ensure every transaction is handled with the highest level of professionalism and care.\nCONTACT US\nWhere You Can\nFind Us\nWith offices in Miami, Lisbon and Madrid, L40° bridges global markets to deliver impactful results. Our expertise and international reach ensure every transaction is handled with the highest level of professionalism and care.\nCONTACT US\nJoin the L40 Brief\nJoin the L40 Brief\nReceive only insights that matter: market analysis, deal deep dives, and exclusive founder events.\nThank you! Your submission has been received!\nOops! Something went wrong while submitting the form.\nOur newsletter Subscribe below to gain access to our exclusive insights. No clutter, no irrelevant content, just valuable updates that matter to you.\nThank you! Your submission has been received!\nOops! Something went wrong while submitting the form.\nServices Sell-side M&A advisory Debt advisory\nInsights\nTransactions\nAbout us About L40 Team FAQs\nL40 operates in the United States under the SEC's M&A broker exemption in Section 15(b)(13) of the Securities Exchange Act. The information and services provided on this website may not be available in all jurisdictions and are not intended for use where their provision or use would violate applicable laws, rules, or regulations. You should contact L40 to confirm the availability of specific services in your jurisdiction before proceeding.\nL40 Partners, Inc. 2025. All rights reserved.\nPrivacy Notice |\nTerms of Service |\nCookies Preferences |\nFollow us:",
  "clean_text": "Transactions INSIGHTS\nABOUT US\nContact Us\nRelated Insights\nNews & Trends\n6/17/2026\nTop SaaS News: August 2025 Recap for Founders\nTop SaaS Industry News: August 2025 Recap for Founders\nAugust 2025 SaaS news: PE bets on platforms, Figma & Circle IPOs reset valuations, and what it means for founders planning their next move.\nNews & Trends\n6/17/2026\nAI Due Diligence: Revolutionizing Deal Assessments\nDiscover how AI due diligence is transforming M&A transactions, enhancing efficiency and accuracy. Read on to understand its impact on the future of deals.\nNews & Trends\n6/17/2026\nWhat to know about AI rollups\nAI Rollups in 2026: What Founders Need to Know\nLearn what AI Rollups are, what buyers want, and what SaaS founders need to know about these type of deals.\nWhere You Can\nFind Us\nWith offices in Miami, Lisbon and Madrid, L40° bridges global markets to deliver impactful results. Our expertise and international reach ensure every transaction is handled with the highest level of professionalism and care.\nCONTACT US\nWhere You Can\nFind Us\nWith offices in Miami, Lisbon and Madrid, L40° bridges global markets to deliver impactful results. Our expertise and international reach ensure every transaction is handled with the highest level of professionalism and care.\nCONTACT US\nJoin the L40 Brief\nJoin the L40 Brief\nReceive only insights that matter: market analysis, deal deep dives, and exclusive founder events.\nThank you! Your submission has been received!\nOops! Something went wrong while submitting the form.\nOur newsletter Subscribe below to gain access to our exclusive insights. No clutter, no irrelevant content, just valuable updates that matter to you.\nThank you! Your submission has been received!\nOops! Something went wrong while submitting the form.\nServices Sell-side M&A advisory Debt advisory\nInsights\nTransactions\nAbout us About L40 Team FAQs\nL40 operates in the United States under the SEC's M&A broker exemption in Section 15(b)(13) of the Securities Exchange Act. The information and services provided on this website may not be available in all jurisdictions and are not intended for use where their provision or use would violate applicable laws, rules, or regulations. You should contact L40 to confirm the availability of specific services in your jurisdiction before proceeding.\nL40 Partners, Inc. 2025. All rights reserved.\nPrivacy Notice |\nTerms of Service |\nCookies Preferences |\nFollow us:",
  "markdown_snapshot_path": "01-SiteV2/content/01-raw/originals/2026-06-25/r-087-vertical-ai-saas-what-founders-need-to-know-in-2026-l40.md",
  "json_snapshot_path": "01-SiteV2/content/01-raw/originals/2026-06-25/r-087-vertical-ai-saas-what-founders-need-to-know-in-2026-l40.json",
  "html_snapshot_path": "",
  "screenshot_path": "",
  "fetch_status": "fetched-readable-text-content-container",
  "extraction_quality": "medium",
  "extraction_method": "content-container",
  "readability_score": 66,
  "extractor_diagnostics": {
    "readability_score": 66,
    "text_length": 2424,
    "paragraph_count": 22,
    "sentence_count": 25,
    "boilerplate_hits": 4,
    "symbol_ratio": 0.0012,
    "replacement_count": 0,
    "replacement_ratio": 0,
    "control_count": 0,
    "control_ratio": 0,
    "binary_marker_count": 0,
    "mojibake_marker_count": 0,
    "binary_contaminated": false,
    "mojibake_contaminated": false,
    "method": "content-container"
  },
  "has_full_text": true,
  "content_length": 2424,
  "fetch_error": "",
  "evidence_completeness": {
    "original_url_status": "present",
    "full_text_status": "present",
    "snapshot_status": "present",
    "hash_status": "present",
    "excerpt_status": "present",
    "markdown_snapshot_status": "will_write",
    "json_snapshot_status": "will_write",
    "evidence_hash": "76b428f0bdd767dc",
    "missing": []
  },
  "raw_qc_decision": "allow",
  "raw_qc_downstream_use": "eligible_after_qc",
  "degradation_reasons": [],
  "source_volatility": "low",
  "community_name": "",
  "capture_scope": "article_text",
  "visible_range": "抓取时页面可见正文 / 讨论文本",
  "evidence_level": "core_evidence_candidate",
  "discovery_source": "",
  "discovery_record": null,
  "source_role": "resolved_original_source",
  "origin_fetch_status": "",
  "paywall_status": "none",
  "block_status": "none",
  "duplicate_status": "unique",
  "url_hash": "e419e9b83422b729",
  "content_hash": "76b428f0bdd767dc",
  "full_text_hash": "76b428f0bdd767dc",
  "semantic_hash": "16dfe57da1a6bfb2",
  "duplicate_of": "",
  "first_seen_at": "2026-06-25T03:26:00.697Z",
  "last_seen_at": "2026-06-25T03:26:00.697Z",
  "update_detected": false,
  "key_excerpts": [
    {
      "type": "workflow_change",
      "text": "# Vertical AI SaaS: What Founders Need to Know in 2026. Illustration for the article: Vertical AI SaaS: What Founders Need to Know in 2025. Founders who have built workflows for specific industries are now exploring the use of AI to automate processes, improve decision-making, and overall, increase the output and value of their traditional services. The pace of AI usage varies by sector, but something is clear across the board: AI is expanding what vertical SaaS platforms can do with the proprietary data of specifi",
      "supports": [
        "daily_observation",
        "heatmap",
        "change",
        "case",
        "trend"
      ],
      "importance": "high",
      "confidence": "medium"
    },
    {
      "type": "company_action",
      "text": "Transactions INSIGHTS ABOUT US Contact Us Related Insights News & Trends 6/17/2026 Top SaaS News: August 2025 Recap for Founders Top SaaS Industry News: August 2025 Recap for Founders August 2025 SaaS news: PE bets on platforms, Figma & Circle IPOs reset valuations, and what it means for founders planning their next move.",
      "supports": [
        "daily_observation",
        "heatmap",
        "change",
        "case",
        "trend"
      ],
      "importance": "medium",
      "confidence": "medium"
    },
    {
      "type": "company_action",
      "text": "News & Trends 6/17/2026 AI Due Diligence: Revolutionizing Deal Assessments Discover how AI due diligence is transforming M&A transactions, enhancing efficiency and accuracy.",
      "supports": [
        "daily_observation",
        "heatmap",
        "change",
        "case",
        "trend"
      ],
      "importance": "medium",
      "confidence": "medium"
    },
    {
      "type": "company_action",
      "text": "Read on to understand its impact on the future of deals.",
      "supports": [
        "daily_observation",
        "heatmap",
        "change",
        "case",
        "trend"
      ],
      "importance": "medium",
      "confidence": "medium"
    },
    {
      "type": "company_action",
      "text": "News & Trends 6/17/2026 What to know about AI rollups AI Rollups in 2026: What Founders Need to Know Learn what AI Rollups are, what buyers want, and what SaaS founders need to know about these type of deals.",
      "supports": [
        "daily_observation",
        "heatmap",
        "change",
        "case",
        "trend"
      ],
      "importance": "medium",
      "confidence": "medium"
    },
    {
      "type": "company_action",
      "text": "Where You Can Find Us With offices in Miami, Lisbon and Madrid, L40° bridges global markets to deliver impactful results.",
      "supports": [
        "daily_observation",
        "heatmap",
        "change",
        "case",
        "trend"
      ],
      "importance": "medium",
      "confidence": "medium"
    }
  ],
  "business_elements": {
    "companies": [
      "keyword search",
      "Tavily"
    ],
    "products": [
      "agent"
    ],
    "people": [],
    "industries": [
      "法律 / 法务"
    ],
    "roles": [
      "CIO / IT 负责人"
    ],
    "workflows": [
      "计费 / 预算管理",
      "部署 / 集成交付"
    ],
    "business_actions": [
      "合作 / 联盟",
      "部署 / 上线"
    ],
    "affected_departments": [
      "IT / 安全",
      "法务"
    ],
    "numbers": [
      "2026",
      "40",
      "2025",
      "0.688",
      "6",
      "17",
      "40 B",
      "15"
    ],
    "quotes": []
  },
  "evidence_seed": {
    "company_actions": [
      "Transactions INSIGHTS ABOUT US Contact Us Related Insights News & Trends 6/17/2026 Top SaaS News: August 2025 Recap for Founders Top SaaS Industry News: August 2025 Recap for Founders August 2025 SaaS news: PE bets on platforms, Figma & Circle IPOs reset valuations, and what it means for founders planning their next move.",
      "News & Trends 6/17/2026 AI Due Diligence: Revolutionizing Deal Assessments Discover how AI due diligence is transforming M&A transactions, enhancing efficiency and accuracy.",
      "Read on to understand its impact on the future of deals."
    ],
    "case_details": [],
    "workflow_changes": [
      "# Vertical AI SaaS: What Founders Need to Know in 2026. Illustration for the article: Vertical AI SaaS: What Founders Need to Know in 2025. Founders who have built workflows for specific industries are now exploring the use of AI to automate processes, improve decision-making, and overall, increase the output and value of their traditional services. The pace of AI usage varies by sector, but something is clear across the board: AI is expanding what vertical SaaS platforms can do with the proprietary data of specifi"
    ],
    "before_after_clues": [
      "可能涉及 计费 / 预算管理 的前后变化，需要二搜补足变化前流程。",
      "可能涉及 部署 / 集成交付 的前后变化，需要二搜补足变化前流程。"
    ],
    "affected_roles": [
      "CIO / IT 负责人"
    ],
    "risks_or_constraints": []
  },
  "guanlan_scores": {
    "importance_type": "important_product_or_service",
    "importance_score": 5,
    "importance_reason": "new product or service; rubric=5 major/platform/industry-shaping",
    "supporting_signals": [
      "commercial_or_risk_context",
      "adoption_context"
    ],
    "novelty": 3,
    "evidence_strength": 4,
    "case_richness": 5,
    "trend_relevance": 4,
    "guanlan_relevance": 5,
    "emerging_signal_score": 3
  },
  "usable_for": {
    "viewpoint": false,
    "case": true,
    "change": true,
    "trend": true,
    "daily_observation": true,
    "heatmap": true,
    "briefing": true,
    "emerging_pool": false,
    "user_feedback_pool": false,
    "watchlist": true
  },
  "pool_routes": [
    "core_pool"
  ],
  "change_action_detected": true,
  "evidence_eligibility": "eligible",
  "evidence_block_reason": "",
  "missing_information": [
    "没有具体客户或真实企业案例"
  ],
  "raw_status": "candidate",
  "copyright_note": "local research archive only",
  "markdown_snapshot": "# Vertical AI SaaS: What Founders Need to Know in 2026 | L40°\n\n- raw_id: R-087\n- original_url: https://www.l40.com/insights/vertical-ai-saas\n- source_name: keyword search / Tavily\n- collected_at: 2026-06-25T03:26:00.697Z\n\n## clean_text\n\nTransactions INSIGHTS\nABOUT US\nContact Us\nRelated Insights\nNews & Trends\n6/17/2026\nTop SaaS News: August 2025 Recap for Founders\nTop SaaS Industry News: August 2025 Recap for Founders\nAugust 2025 SaaS news: PE bets on platforms, Figma & Circle IPOs reset valuations, and what it means for founders planning their next move.\nNews & Trends\n6/17/2026\nAI Due Diligence: Revolutionizing Deal Assessments\nDiscover how AI due diligence is transforming M&A transactions, enhancing efficiency and accuracy. Read on to understand its impact on the future of deals.\nNews & Trends\n6/17/2026\nWhat to know about AI rollups\nAI Rollups in 2026: What Founders Need to Know\nLearn what AI Rollups are, what buyers want, and what SaaS founders need to know about these type of deals.\nWhere You Can\nFind Us\nWith offices in Miami, Lisbon and Madrid, L40° bridges global markets to deliver impactful results. Our expertise and international reach ensure every transaction is handled with the highest level of professionalism and care.\nCONTACT US\nWhere You Can\nFind Us\nWith offices in Miami, Lisbon and Madrid, L40° bridges global markets to deliver impactful results. Our expertise and international reach ensure every transaction is handled with the highest level of professionalism and care.\nCONTACT US\nJoin the L40 Brief\nJoin the L40 Brief\nReceive only insights that matter: market analysis, deal deep dives, and exclusive founder events.\nThank you! Your submission has been received!\nOops! Something went wrong while submitting the form.\nOur newsletter Subscribe below to gain access to our exclusive insights. No clutter, no irrelevant content, just valuable updates that matter to you.\nThank you! Your submission has been received!\nOops! Something went wrong while submitting the form.\nServices Sell-side M&A advisory Debt advisory\nInsights\nTransactions\nAbout us About L40 Team FAQs\nL40 operates in the United States under the SEC's M&A broker exemption in Section 15(b)(13) of the Securities Exchange Act. The information and services provided on this website may not be available in all jurisdictions and are not intended for use where their provision or use would violate applicable laws, rules, or regulations. You should contact L40 to confirm the availability of specific services in your jurisdiction before proceeding.\nL40 Partners, Inc. 2025. All rights reserved.\nPrivacy Notice |\nTerms of Service |\nCookies Preferences |\nFollow us:\n\n## full_text\n\nTransactions INSIGHTS\nABOUT US\nContact Us\nRelated Insights\nNews & Trends\n6/17/2026\nTop SaaS News: August 2025 Recap for Founders\nTop SaaS Industry News: August 2025 Recap for Founders\nAugust 2025 SaaS news: PE bets on platforms, Figma & Circle IPOs reset valuations, and what it means for founders planning their next move.\nNews & Trends\n6/17/2026\nAI Due Diligence: Revolutionizing Deal Assessments\nDiscover how AI due diligence is transforming M&A transactions, enhancing efficiency and accuracy. Read on to understand its impact on the future of deals.\nNews & Trends\n6/17/2026\nWhat to know about AI rollups\nAI Rollups in 2026: What Founders Need to Know\nLearn what AI Rollups are, what buyers want, and what SaaS founders need to know about these type of deals.\nWhere You Can\nFind Us\nWith offices in Miami, Lisbon and Madrid, L40° bridges global markets to deliver impactful results. Our expertise and international reach ensure every transaction is handled with the highest level of professionalism and care.\nCONTACT US\nWhere You Can\nFind Us\nWith offices in Miami, Lisbon and Madrid, L40° bridges global markets to deliver impactful results. Our expertise and international reach ensure every transaction is handled with the highest level of professionalism and care.\nCONTACT US\nJoin the L40 Brief\nJoin the L40 Brief\nReceive only insights that matter: market analysis, deal deep dives, and exclusive founder events.\nThank you! Your submission has been received!\nOops! Something went wrong while submitting the form.\nOur newsletter Subscribe below to gain access to our exclusive insights. No clutter, no irrelevant content, just valuable updates that matter to you.\nThank you! Your submission has been received!\nOops! Something went wrong while submitting the form.\nServices Sell-side M&A advisory Debt advisory\nInsights\nTransactions\nAbout us About L40 Team FAQs\nL40 operates in the United States under the SEC's M&A broker exemption in Section 15(b)(13) of the Securities Exchange Act. The information and services provided on this website may not be available in all jurisdictions and are not intended for use where their provision or use would violate applicable laws, rules, or regulations. You should contact L40 to confirm the availability of specific services in your jurisdiction before proceeding.\nL40 Partners, Inc. 2025. All rights reserved.\nPrivacy Notice |\nTerms of Service |\nCookies Preferences |\nFollow us:\n\n## extraction_diagnostics\n\n- extraction_method: content-container\n- readability_score: 66\n- fetch_status: fetched-readable-text-content-container\n- extraction_quality: medium\n\n## key_excerpts\n\n1. [workflow_change / daily_observation, heatmap, change, case, trend / high] # Vertical AI SaaS: What Founders Need to Know in 2026. Illustration for the article: Vertical AI SaaS: What Founders Need to Know in 2025. Founders who have built workflows for specific industries are now exploring the use of AI to automate processes, improve decision-making, and overall, increase the output and value of their traditional services. The pace of AI usage varies by sector, but something is clear across the board: AI is expanding what vertical SaaS platforms can do with the proprietary data of specifi\n2. [company_action / daily_observation, heatmap, change, case, trend / medium] Transactions INSIGHTS ABOUT US Contact Us Related Insights News & Trends 6/17/2026 Top SaaS News: August 2025 Recap for Founders Top SaaS Industry News: August 2025 Recap for Founders August 2025 SaaS news: PE bets on platforms, Figma & Circle IPOs reset valuations, and what it means for founders planning their next move.\n3. [company_action / daily_observation, heatmap, change, case, trend / medium] News & Trends 6/17/2026 AI Due Diligence: Revolutionizing Deal Assessments Discover how AI due diligence is transforming M&A transactions, enhancing efficiency and accuracy.\n4. [company_action / daily_observation, heatmap, change, case, trend / medium] Read on to understand its impact on the future of deals.\n5. [company_action / daily_observation, heatmap, change, case, trend / medium] News & Trends 6/17/2026 What to know about AI rollups AI Rollups in 2026: What Founders Need to Know Learn what AI Rollups are, what buyers want, and what SaaS founders need to know about these type of deals.\n6. [company_action / daily_observation, heatmap, change, case, trend / medium] Where You Can Find Us With offices in Miami, Lisbon and Madrid, L40° bridges global markets to deliver impactful results.\n"
}
